[{"iteration":{"value":"Iteration 33"},"complexity":{"value":"5"},"team":{"value":"DX"},"status":{"value":"🔖 Ready"},"qa":null,"content":{"title":"Add advanced [Guide or Article] The ExtensibleFallbackHandler","assignees":{"nodes":[{"value":"valle-xyz"}]}}},{"iteration":{"value":"Iteration 33"},"complexity":{"value":"5"},"team":{"value":"DX"},"status":{"value":"🔖 Ready"},"qa":null,"content":{"title":"Add advanced [Guide or article] Deployments on multiple Chains","assignees":{"nodes":[{"value":"valle-xyz"}]}}}]